{"id": "5855337732204683022", "type": 1, "user": 3118, "time": 1363273253, "content": "10年作品<br/>当我还是萌妹子的时候，我总是揪心一个问题，我出了御姐，我是不是就是一个御姐了。有一天我就为了证明自己还年轻，就跑教室里拍了一组miku的cos，然后到处问，我到底是妹子还是御姐气质。现在看来，当时真是傻到可爱，现在我顶一张大妈脸都敢各种出妹子，那时候却觉得自己好老啊只能出御姐伪妹子。果然我应了，小时候渴望长大，偷穿妈妈衣服跟鞋用化妆品，等到真的可以用上这些的年龄，却想尽办法的穿鲜艳的衣服显示自己的年轻 这现象。 <br/>不过这后悔也没用，毕竟我已经过了脸上不护理就能捏出水的年纪，时间也倒不回去，只能疯狂拍着各种补水护肤品在这里吐个槽，回头加重粉底和磨皮了。<br/>初音未来 cn: 水狐", "tags": [34, 399, 32], "images": [{"id": -7000402, "w": 597, "h": 900, "name": "5141e4518441d", "format": 1}]}