{"id": "6047344674669092622", "type": 1, "user": 32394, "time": 1407978353, "content": "呵呵，我又来作死了！这一套本来准备发在worldcosplay的\\\\(^o^)/ [在worldcosplay注册了个新号]\u003Cbr/\u003E可是为啥又发在这里呢？因为发布不了啊！发一次死一次机！！泥煤卡出翔了！！\u003Cbr/\u003E跟上次一套是同一天出的，一个白天的一个夜景\u003Cbr/\u003E(─.─||| 别问我为什么分开发，当然是因为摄影君不同啊哇哈哈&lt;垢。。 \u003Cbr/\u003E可能是白天比较闲的原因，产出的片还挺多~&gt;_&lt;~+\u003Cbr/\u003E栗山未来 cn: 脑洞模式的悦w\u003Cbr/\u003E摄影：乔巴 | 化妆：烈旭 | 后期：繁花梦 | 协力：翎鸦_karas", "tags": [399, 172, 173], "images": [{"id": 8622158, "w": 3744, "h": 5616, "name": "53ec0a694878c", "format": 1, "size": 1440560}, {"id": 8622173, "w": 3744, "h": 5616, "name": "53ec0a704878d", "format": 1, "size": 1392749}, {"id": 8622180, "w": 5472, "h": 3648, "name": "53ec0a764878e", "format": 1, "size": 1779771}, {"id": 8622191, "w": 5472, "h": 3648, "name": "53ec0a804878f", "format": 1, "size": 1782098}, {"id": 8622203, "w": 4608, "h": 3158, "name": "53ec0a8848790", "format": 1, "size": 1019614}, {"id": 8622240, "w": 3457, "h": 4280, "name": "53ec0a9948793", "format": 1, "size": 1076646}, {"id": 8622252, "w": 5616, "h": 3744, "name": "53ec0a9f48794", "format": 1, "size": 1425920}, {"id": 8622259, "w": 3744, "h": 5616, "name": "53ec0aa548795", "format": 1, "size": 1258166}, {"id": 8622267, "w": 3744, "h": 5616, "name": "53ec0aab48796", "format": 1, "size": 1711100}, {"id": 8622279, "w": 5616, "h": 3744, "name": "53ec0ab648797", "format": 1, "size": 833477}]}