{"id": "6116868336786628366", "type": 1, "user": 5951, "time": 1424165592, "content": "去年暑假拍的片子，发了很久不过没放到半次元 \u003Cbr/\u003E重庆的天气真是热死人，而且蚊子一大堆，果然我们是高温小战士\u003Cbr/\u003E现在看片子觉得好渣，果然是那会太胖了肉好多，感谢后期不杀之恩\u003Cbr/\u003E日暮戈薇 cn: 扣子_梨棠绮扇，犬夜叉 cn: 胤野，桔梗 cn: 沫子咊家戒子\u003Cbr/\u003E摄影：白叔 | 化妆：堇色 黑宫 | 后期：苏苏", "tags": [399, 378, 1878, 6518], "images": [{"id": 7923474, "w": 3531, "h": 5397, "name": "10974720b68611e483e733f499de1abb", "format": 1}, {"id": 7923373, "w": 3648, "h": 5472, "name": "e4e1b3e0b68511e483e733f499de1abb", "format": 1}, {"id": 7923704, "w": 3648, "h": 5472, "name": "60b7dca0b68711e483e733f499de1abb", "format": 1}, {"id": 7922955, "w": 5472, "h": 3648, "name": "eb3f4240b68311e483e733f499de1abb", "format": 1}, {"id": 7923200, "w": 4500, "h": 3000, "name": "d47e68f0b68411e483e733f499de1abb", "format": 1}, {"id": 7923318, "w": 3200, "h": 4800, "name": "4328cb10b68511e483e733f499de1abb", "format": 1}, {"id": 7923352, "w": 5472, "h": 3648, "name": "85e94380b68511e483e733f499de1abb", "format": 1}, {"id": 7923532, "w": 3648, "h": 5472, "name": "66263390b68611e483e733f499de1abb", "format": 1}, {"id": 7923591, "w": 5472, "h": 3648, "name": "df050ac0b68611e483e733f499de1abb", "format": 1}]}