{"id": "6143652057787162382", "type": 1, "user": 43067, "time": 1430401663, "content": "学校组织了个书签制作大赛，总之要挂出去，于是乎。。。这么好的传教机会，我会错过吗？\u003Cbr/\u003E\u003Cbr/\u003E还有请忽视那有点过于简单明白的解说，因为是传教用的嘛～", "tags": [5798, 9, 1124, 94, 1270, 23052, 23053, 100, 1113], "images": [{"id": 1856628, "w": 562, "h": 750, "name": "2becb9f0ef3f11e4a214c3b22f7fabd2", "format": 1}, {"id": 1856658, "w": 563, "h": 750, "name": "2ca20030ef3f11e4a214c3b22f7fabd2", "format": 1}, {"id": 1856684, "w": 563, "h": 750, "name": "2cc71460ef3f11e4a214c3b22f7fabd2", "format": 1}, {"id": 1856710, "w": 563, "h": 750, "name": "2ce6aa50ef3f11e4a214c3b22f7fabd2", "format": 1}, {"id": 1856734, "w": 562, "h": 750, "name": "2d049290ef3f11e4a214c3b22f7fabd2", "format": 1}]}