{"id": "6247201803738308366", "type": 1, "user": 192605, "time": 1454511217, "content": "重新发一次，之前那个太多bug了，话说最严重的问题是我分不清左右orz…有些bug是改不了的了大家见谅QAQ<br/>还是废话一下吧，安娜这个角色对我来说真的是难度系数超大的一个挑战，少女我已经觉得很难萝莉就更不用说了orz出这个角色真的是准备了很久，当初很犹豫到底要不要出不过最后还是选择挑战，毕竟对这个人物真的很喜欢，从第一部纠结到第二部orz 感谢摄影，希望大家喜欢！<br/>栉名安娜 cn: 随音kaze<br/>摄影：星光丶艾森瑞尔斯 | 化妆：随音kaze | 后期：随音kaze | 协力：星光丶艾森瑞尔斯", "tags": [399, 140, 51108, 2947, 56095], "images": [{"id": -7045739, "w": 4608, "h": 3072, "name": "5cd53750ca8011e5a72e3f612469c322", "format": 1, "size": 1161577}, {"id": -7045738, "w": 2500, "h": 1518, "name": "6c06d580ca8011e5a72e3f612469c322", "format": 1, "size": 361812}, {"id": -7045737, "w": 1786, "h": 2500, "name": "7161d610ca8011e5a72e3f612469c322", "format": 1, "size": 442367}, {"id": -7045741, "w": 2500, "h": 3720, "name": "78898050ca8011e5a72e3f612469c322", "format": 1, "size": 753947}, {"id": -7045740, "w": 2500, "h": 1662, "name": "7faff210ca8011e5a72e3f612469c322", "format": 1, "size": 409856}, {"id": -7045742, "w": 2500, "h": 1613, "name": "850fd4a0ca8011e5a72e3f612469c322", "format": 1, "size": 510871}, {"id": -7045744, "w": 1662, "h": 2500, "name": "89d28cd0ca8011e5a72e3f612469c322", "format": 1, "size": 436780}, {"id": -7045743, "w": 2500, "h": 1548, "name": "8f2ffe60ca8011e5a72e3f612469c322", "format": 1, "size": 489782}]}