{"id": "6318453777875623694", "type": 1, "user": 992222, "time": 1471100860, "content": "第二次出正片还是小紧张，估计表情动作废是改不了了嘤_(:_」∠)如果有意见就多多砸过来吧(:3▓▒\u003Cbr/\u003E黑猫 cn: 羽奏", "tags": [399, 4251, 356], "images": [{"id": 2234259, "w": 750, "h": 1125, "name": "ef783464b221410c87a4063d67be4d39", "format": 1}, {"id": 2234291, "w": 750, "h": 1125, "name": "bd624e53ea7f466d99423856b87e7bf4", "format": 1}, {"id": 2234323, "w": 750, "h": 1125, "name": "8432a2ecd70c4b33b18024b4c0db4d39", "format": 1}, {"id": 2234353, "w": 750, "h": 1125, "name": "9e6b197e558a4a7399b6a7af719a05c0", "format": 1}, {"id": 2234391, "w": 750, "h": 1141, "name": "d7375d2276dc455f8674a030f46b35d3", "format": 1}, {"id": 2234421, "w": 864, "h": 565, "name": "cfa839b0d98c4fe0b570a580b0631b5c", "format": 1}]}