{"id": "6322929765158248206", "type": 1, "user": 1661863, "time": 1472143007, "content": "【古都九色舞团】\u003Cbr/\u003E这是五月拍的了，拖了很久现在才产出来\u003Cbr/\u003E当天是一直在下雨，我们是在等到了雨停凌晨才录的，妹子们都有点困了家长也都不放心过来找我们，真的是很不容易，不好的地方欢迎大家指出来~但不接受喷颜喷身材谢谢米娜桑\u003Cbr/\u003E【下面是妹子们cn和微博】（舞团收人欢迎B站私信和微博戳洛宝）\u003Cbr/\u003E妮可：洛宝@洛宝SAMA\u003Cbr/\u003E会长：深井@是深井不是神经\u003Cbr/\u003E凛喵：果子李@煎饼果子李w\u003Cbr/\u003E小鸟：泠溦\u003Cbr/\u003E希魔：格林@格林林林林-\u003Cbr/\u003E花阳：点点\u003Cbr/\u003E海爷：碧落@碧落落Lily-天界四米八\u003Cbr/\u003E果果：软软@simple软软r \u003Cbr/\u003E真姬：涟漪\u003Cbr/\u003Ehttps://www.bilibili.com/video/av6002404/\u003Cbr/\u003E矢泽妮可 cn: 洛宝SAMA，园田海未 cn: 碧落，小泉花阳 cn: 点点，东条希 cn: 格林，绚濑绘里 cn: 深井，穗乃果 cn: 软软，南小鸟 cn: 泠溦，西木野真姬 cn: 涟漪，星空凛 cn: 果子李\u003Cbr/\u003E摄影：地球人 | 化妆：自理 | 后期：格林 | 协力：谢耳朵", "tags": [399, 1191, 15572, 21637, 1872, 102431, 2056, 2220, 2546, 2547, 1449], "images": [{"id": 4237531, "w": 5776, "h": 3792, "name": "103a49606ae111e68a3849d26ce88193", "format": 1}]}