{"id": "6323696502719930126", "type": 1, "user": 480014, "time": 1472321527, "content": "有时间的话 会再把剩下的几只补上\u003Cbr/\u003Ep站&gt;&gt;&gt;http://www.pixiv.net/member_illust.php?mode=medium&amp;illust_id=58682804\u003Cbr/\u003E微博&gt;&gt;&gt;http://weibo.com/2944969455/profile?rightmod=1&amp;wvr=6&amp;mod=personinfo&amp;is_all=1", "tags": [5798, 1294, 1138, 94, 1291, 22686, 102988, 5397, 13095, 40872, 14207], "images": [{"id": 4552229, "w": 3840, "h": 975, "name": "4a3f8be06c7911e6868d7d004a89fe2d", "format": 1}]}