{"id": "6368421620670816014", "type": 1, "user": 40631, "time": 1482734905, "content": "又是一年的结尾，每年暑假拍的片子都要拖到年底才有动力修。。<br/>感谢鲍受受和老哥小宇喵被我从空调房里拖出去拍情怀，还有轮叔一如既往的精神支持技术支持和人力支持。<br/>过了圣诞节，就是新的一年了，希望我们还能一起搞事情【wink~<br/>恵飞须泽胡桃 cn: Annsir_暗瑟，若狭悠里 cn: 深海鲍<br/>摄影：tiger 风火轮 | 化妆：Annsir_暗瑟 小宇猫 | 后期：Annsir_暗瑟 | 协力：EX_翼", "tags": [29199, 399, 29200, 191093], "images": [{"id": -7067148, "w": 2688, "h": 4018, "name": "3d717610cb3511e6bead317822243a14", "format": 1, "size": 495624}, {"id": -7067155, "w": 4288, "h": 2436, "name": "403773e0cb3511e6bead317822243a14", "format": 1, "size": 797646}, {"id": -7067156, "w": 2506, "h": 4336, "name": "433a7ab0cb3511e6bead317822243a14", "format": 1, "size": 729881}, {"id": -7067151, "w": 4043, "h": 4971, "name": "477abc70cb3511e6bead317822243a14", "format": 1, "size": 992008}, {"id": -7067152, "w": 4018, "h": 5368, "name": "4d164870cb3511e6bead317822243a14", "format": 1, "size": 864874}, {"id": -7067149, "w": 4018, "h": 6701, "name": "514bdbd0cb3511e6bead317822243a14", "format": 1, "size": 1369103}, {"id": -7067153, "w": 2688, "h": 7589, "name": "5836f240cb3511e6bead317822243a14", "format": 1, "size": 962160}, {"id": -7067150, "w": 3975, "h": 9793, "name": "b0f17c20cb3511e6bead317822243a14", "format": 1, "size": 2746756}, {"id": -7067154, "w": 2518, "h": 10480, "name": "b5989600cb3511e6bead317822243a14", "format": 1, "size": 2713194}]}