{"id": "6374761512090754830", "type": 1, "user": 516810, "time": 1484211026, "content": "妆娘-洺茶\u003Cbr/\u003E后期-阿余\u003Cbr/\u003E依然产片较少/新的一年仍然爱着小姐姐\u003Cbr/\u003E&gt;&gt;&gt;&gt;请呼唤我的名字 我将爱上你\u003Cbr/\u003E\u003Cbr/\u003E东条希 cn: 八重云_", "tags": [399, 2097, 51, 1191, 37905, 2546], "images": [{"id": 1865950, "w": 2480, "h": 23622, "name": "yvi5shqjqpmqtneqlbc96jgkkgewqnww", "format": 1}, {"id": 1865982, "w": 4928, "h": 3264, "name": "jzrfgzhxbwlamdfjj7dlg8yi7bq6r58a", "format": 1}, {"id": 1866013, "w": 3264, "h": 4928, "name": "u6xkbcdhq5pzfbbqud1w78n0comxcdik", "format": 1}, {"id": 1866050, "w": 3264, "h": 4928, "name": "eds4hukxjkdf840w0gpvcskxnrp8ibau", "format": 1}, {"id": 1866084, "w": 3264, "h": 4928, "name": "pdoov8k0yvsycodnjbzbnzjplmp40dul", "format": 1}, {"id": 1866110, "w": 4928, "h": 3264, "name": "giwwdwzzfshs7aeod3eourwuunwlquxd", "format": 1}, {"id": 1866141, "w": 4928, "h": 3264, "name": "fmapd92iysyc8l2r3ppsaoh7hyfq96v6", "format": 1}]}