{"id": "6437895246419353358", "type": 1, "user": 961514, "time": 1498910494, "content": "西尾维新大辞展 部分贩售商品公开 有之前公布过的Q版战场原黑仪和KISSSHOT ​​​​", "tags": [971, 4668, 7748], "images": [{"id": 5136259, "w": 471, "h": 444, "name": "3cd279e05e5411e7b5f67dad86f913af", "format": 1, "size": 32947}, {"id": 5136275, "w": 467, "h": 442, "name": "3e922b405e5411e7b5f67dad86f913af", "format": 1, "size": 40104}, {"id": 5136290, "w": 474, "h": 443, "name": "401aee205e5411e7b5f67dad86f913af", "format": 1, "size": 29901}, {"id": 5136308, "w": 471, "h": 441, "name": "41a908305e5411e7b5f67dad86f913af", "format": 1, "size": 30159}, {"id": 5136322, "w": 470, "h": 442, "name": "4303b6305e5411e7b5f67dad86f913af", "format": 1, "size": 21842}, {"id": 5136340, "w": 481, "h": 441, "name": "444beda05e5411e7b5f67dad86f913af", "format": 1, "size": 42010}, {"id": 5136358, "w": 467, "h": 448, "name": "45913ee05e5411e7b5f67dad86f913af", "format": 1, "size": 36667}, {"id": 5136376, "w": 470, "h": 446, "name": "46f5ff005e5411e7b5f67dad86f913af", "format": 1, "size": 21256}]}