{"id": "6451871143014981390", "type": 1, "user": 1108862, "time": 1502164511, "content": "微博：regina楠w\u003Cbr/\u003E弥 cn: 楠", "tags": [399, 169, 19656], "images": [{"id": 7823389, "w": 640, "h": 959, "name": "uuxz0rctu4rdqtg2c49qsgdxh69jc1ph", "format": 1}, {"id": 7823410, "w": 640, "h": 959, "name": "tgarqhg00ajq5mriee6jqt93zcnymk9v", "format": 1}, {"id": 7823421, "w": 640, "h": 959, "name": "ur44qsv1lb8hauhkujdk7gyjfnlvacya", "format": 1}, {"id": 7823429, "w": 959, "h": 640, "name": "uhe3kiyhxcz3pw5vthkags1yhamz72l9", "format": 1}, {"id": 7823438, "w": 640, "h": 959, "name": "6y800oywxxxnqlgpirad7uvfi47doacv", "format": 1}, {"id": 7823454, "w": 959, "h": 640, "name": "cpmb5lkylf1beuzypiwy6dix11r4xmam", "format": 1}, {"id": 7823464, "w": 959, "h": 640, "name": "uaxw6zzvhyfbkz19t51eu7bd0vxeqiox", "format": 1}, {"id": 7823472, "w": 640, "h": 959, "name": "4x3onpldivkuxk34fifnz5wjlbhnzfdz", "format": 1}, {"id": 7823481, "w": 640, "h": 959, "name": "kaxqis91emkimtw1rfcmtinjbnjnis1f", "format": 1}]}