{"id": "6465308665460055822", "type": 1, "user": 1969946, "time": 1505293178, "content": "泰兰德：“你看到我的猫头鹰了么？哦，她在这儿呢~”\u003Cbr/\u003E国外妹纸Narga的魔兽世界cos作品，摄影by Aoki ​​​​\u003Cbr/\u003E像是游戏里走出来的！", "tags": [4695, 399, 67, 3399], "images": [{"id": 4428466, "w": 690, "h": 460, "name": "dc96a7c0986111e79ba647bac9a7af64", "format": 1, "size": 37006}, {"id": 4428489, "w": 690, "h": 460, "name": "ddd2f850986111e79ba647bac9a7af64", "format": 1, "size": 46343}, {"id": 4428516, "w": 690, "h": 460, "name": "ddf155c0986111e79ba647bac9a7af64", "format": 1, "size": 42384}, {"id": 4428549, "w": 690, "h": 460, "name": "de1aafb0986111e79ba647bac9a7af64", "format": 1, "size": 56430}, {"id": 4428575, "w": 690, "h": 460, "name": "decc7380986111e79ba647bac9a7af64", "format": 1, "size": 49705}, {"id": 4428605, "w": 690, "h": 460, "name": "df042550986111e79ba647bac9a7af64", "format": 1, "size": 46273}]}