{"id": "6537619047163363598", "type": 1, "user": 1122247, "time": 1522158050, "content": "🌸和喜欢的人天长地久是一件非常好的事。\u003Cbr/\u003E🌸如果自己喜欢的人能喜欢自己是再好不过了。\u003Cbr/\u003E🌸不过，只要我喜欢的人能够幸福就好了。\u003Cbr/\u003E\u003Cbr/\u003E\u003Cbr/\u003E\u003Cbr/\u003E\u003Cbr/\u003E大家辛苦了！（鞠躬）这套明明拍的是樱花233333预告一点樱花都没有是不是突然反差萌（滚）and希望大家像小樱一样乐观对待自己的每一个人生足迹❤️爱你们❤️\u003Cbr/\u003E木之本樱 cn: 花吻吻酱，大道寺知世 cn: whitch", "tags": [399, 230, 227, 848, 1123], "images": [{"id": 4917391, "w": 3086, "h": 4629, "name": "wac9ko0iyzoqcc19kd1vofayfaoqyg8y", "format": 1, "size": 1728029}]}