{"id": "6645816256786071815", "type": 1, "user": 99045907005, "time": 1547349676, "content": "咸鱼佬教你如何快速的摸一张简单sakura\u003Cbr\u003E1意识流打型\u003Cbr\u003E2稍微调整一下上固色\u003Cbr\u003E3稍微勾下线\u003Cbr\u003E4加点细节手工 是不是很快？", "tags": [612, 1947, 5798, 38084, 91], "images": [{"id": 16484596, "w": 2894, "h": 4093, "name": "7o2b6entvnmvrwo7flcncdth2hgn9z9j", "format": 1, "size": 417382}, {"id": 16484599, "w": 2894, "h": 4093, "name": "myowjkgiw6oy3lg6j6mpqkogj4rjdafi", "format": 1, "size": 311688}, {"id": 16484598, "w": 2894, "h": 4093, "name": "sjnh4t6c8ftwo8irqffdotlymdgqlbzm", "format": 1, "size": 233315}, {"id": 16484597, "w": 2894, "h": 4093, "name": "umb4hkzwnn5e7qbgyhi8cxnnestghm8u", "format": 1, "size": 323407}]}