{"id": "6677795947163943180", "type": 1, "user": 1209237, "time": 1554795528, "content": "-我呢<br><br> 正在努力的<br> 向你靠近", "tags": [492, 567, 79246], "images": [{"id": -7129160, "w": 3781, "h": 5816, "name": "qtnoed9jehp7jrbs5bdhbjuw7er4xwlg", "format": 1}, {"id": -7129159, "w": 3829, "h": 5744, "name": "nsn3mxeoop22nfpe2bcqs1pmcletvvpm", "format": 1}, {"id": -7129158, "w": 5744, "h": 3829, "name": "frusl5inmvfrj9pcadxeab9gyyyzfuu9", "format": 1}, {"id": -7129157, "w": 5744, "h": 3829, "name": "rloc6z62iee8qitkrcgjrtq3kszvt1ec", "format": 1}, {"id": -7129156, "w": 3829, "h": 5744, "name": "jxv82qqwanzjhpncadafyiwi22jy1o7v", "format": 1}, {"id": -7129155, "w": 3829, "h": 5744, "name": "ct9uaj8opqjbtj6rlazvtiaa0k9nmv5t", "format": 1}, {"id": -7129154, "w": 3829, "h": 5744, "name": "vhllqvmromq2krollajdg5onul8hzenm", "format": 1}, {"id": -7129153, "w": 5744, "h": 3829, "name": "wqcsixlxybcjg1kdghbs3gthjpbguzo5", "format": 1}, {"id": -7129152, "w": 3829, "h": 5744, "name": "q2beyvzuithrwam8nh0cjt26elbzbzti", "format": 1}, {"id": -7129151, "w": 5744, "h": 3829, "name": "mcfmk4nq2uapq6uj0dqza6z4juhyddyv", "format": 1}, {"id": -7129150, "w": 3829, "h": 5744, "name": "wzfdgqkvn9uer0nryopmf9uycygyeexj", "format": 1}, {"id": -7129149, "w": 3829, "h": 5744, "name": "mge6rigfg1zcu9gvfinmyd3cbvolg6jt", "format": 1}]}