{"id": "6720482058524688643", "type": 1, "user": 100252934015, "time": 1564734163, "content": "求K ！ ＃ZF19场照＃＃Re:从零开始的异世界生活＃＃蕾姆cos＃<br><br><br>“我那么诱人 昴君应该会对我心动呢”  <br>“但是蕾姆也很喜欢姐姐呐”<br>“要不她们都属于蕾姆好了”<br><br><br>蕾姆: 原op<br>妆面／拉姆: 轩鸑<br>摄影／后期: 嘎嘎", "tags": [71693, 399], "images": [{"id": -7141921, "w": 224, "h": 240, "name": "8c40206d902649618f9803b803efeafd", "format": 2}, {"id": -7141920, "w": 638, "h": 936, "name": "b60dfb3f16ef4a3db55ea619fb11a7ae", "format": 2}, {"id": -7141919, "w": 427, "h": 640, "name": "0769259b19f4406d9c255f173b63835e", "format": 1}, {"id": -7141918, "w": 428, "h": 640, "name": "d4fe9080b1674776a44e44200e162fcb", "format": 1}, {"id": -7141917, "w": 427, "h": 640, "name": "039d5cbb35494b9e84a13a329c5ab0f0", "format": 1}, {"id": -7141916, "w": 427, "h": 640, "name": "8cd022e0675d4f58b1d42edceefafe55", "format": 1}]}