{"id": "6804801963541152007", "type": 1, "user": 189577, "time": 1584366421, "content": "【剑网3 | 万花】<br>春兰秋菊夏清风，三星望月挂夜空。<br>不求独避风雨外，只笑桃源非梦中。<br><br>摄影：@梓葵引 <br><br>儒风：词.<br>燕云：青石子<br><br>协力：@昼行灯 <br><br>后期：@子墨非白<br>排版：@总裁叶宝宝 <br><br>又出了一次花姐，仍然是葵花花的脑洞，这次是正儿八经的百合片（？），感谢支持~<br><br>拍摄时间：2019年1月26日<br>拍摄地点：光影奇缘工作室", "tags": [1369, 48675, 57, 342, 399, 140110, 316, 20325805, 20480135], "images": [{"id": -7175988, "w": 3648, "h": 5472, "name": "0989bab06b2311eaa1823f9840ae7ad5", "format": 1, "size": 2636445}, {"id": -7175982, "w": 5472, "h": 3648, "name": "0a62ee10677d11eaae8391c644e854d0", "format": 1, "size": 3378024}, {"id": -7175983, "w": 3648, "h": 5472, "name": "1ff42b90677d11eaae8391c644e854d0", "format": 1, "size": 2413512}, {"id": -7175984, "w": 5472, "h": 3648, "name": "4060f390677d11eaae8391c644e854d0", "format": 1, "size": 2574800}, {"id": -7175977, "w": 5472, "h": 3648, "name": "73d34520677d11eaae8391c644e854d0", "format": 1, "size": 2360736}, {"id": -7175986, "w": 2362, "h": 6970, "name": "7f68d300678c11eaae8391c644e854d0", "format": 1, "size": 2133123}, {"id": -7175987, "w": 2362, "h": 11708, "name": "8be08150678c11eaae8391c644e854d0", "format": 1, "size": 3539654}, {"id": -7175978, "w": 2362, "h": 7995, "name": "a958b4b0677c11eaae8391c644e854d0", "format": 1, "size": 2360967}, {"id": -7175985, "w": 3648, "h": 5472, "name": "acc8dfc0677d11eaae8391c644e854d0", "format": 1, "size": 2585023}, {"id": -7175979, "w": 2362, "h": 11020, "name": "beeb78d0677c11eaae8391c644e854d0", "format": 1, "size": 3488563}, {"id": -7175980, "w": 5472, "h": 3648, "name": "deabad20677c11eaae8391c644e854d0", "format": 1, "size": 2676068}, {"id": -7175981, "w": 3648, "h": 5472, "name": "f13a5900677c11eaae8391c644e854d0", "format": 1, "size": 2544616}]}