{"id": "6834147920829219085", "type": 1, "user": 627143, "time": 1591199059, "content": "#cos正片# #lovelive!# #lovelivecos# #绚濑绘里cos##cosplay[超话]##二点五次元[超话]# <br>【职业觉醒-绚濑绘里】<br>绚濑绘里：夜喵梓<br>妆面：自理<br>摄影/后期：@喂你吃虾饺不好吗<br>服装：@喵屋小铺 <br>夜景的怪盗绘里OvO", "tags": [399, 1191, 2547], "images": [{"id": -7188162, "w": 4000, "h": 6000, "name": "0d3f7b40a5b111ea9c24bbb8a73d72d2", "format": 1, "size": 2422891}, {"id": -7188163, "w": 4000, "h": 6000, "name": "134058c0a5b111ea9c24bbb8a73d72d2", "format": 1, "size": 2895036}, {"id": -7188164, "w": 4000, "h": 6000, "name": "199103f0a5b111ea9c24bbb8a73d72d2", "format": 1, "size": 2901032}, {"id": -7188165, "w": 6000, "h": 4000, "name": "1ff907b0a5b111ea9c24bbb8a73d72d2", "format": 1, "size": 2810471}, {"id": -7188166, "w": 4000, "h": 6000, "name": "25d19cb0a5b111ea9c24bbb8a73d72d2", "format": 1, "size": 3062682}, {"id": -7188167, "w": 4739, "h": 3570, "name": "28dfa000a5b111ea9c24bbb8a73d72d2", "format": 1, "size": 2128271}, {"id": -7188168, "w": 4000, "h": 6000, "name": "2d070290a5b111ea9c24bbb8a73d72d2", "format": 1, "size": 3107155}, {"id": -7188169, "w": 4000, "h": 6000, "name": "316887f0a5b111ea9c24bbb8a73d72d2", "format": 1, "size": 3204153}, {"id": -7188170, "w": 4000, "h": 6000, "name": "35d1ae70a5b111ea9c24bbb8a73d72d2", "format": 1, "size": 3083219}]}