{"id": "6847844859718409220", "type": 1, "user": 2823159397752059, "time": 1594388126, "content": "「舞女」玛格丽莎.泽莱\u003Cbr\u003E那个尖顶帐篷里似乎有我向往的一切。鲜花，华服，掌声...还有英俊的微笑小丑。\u003Cbr\u003E一张照片，一位年长女子与黑色头发的少女并排站着，尽管穿着最廉价的棉布连衣裙，也无法使少女的娇艳容貌褪色半分。\u003Cbr\u003E我喜欢在舞台上跳舞，那种感觉好极了。", "tags": [396761, 296504, 1285], "images": [{"id": 84606624, "w": 5064, "h": 3072, "name": "08e399c2c78f40b0939617cf0e6da823", "format": 1, "size": 560089}, {"id": 84606623, "w": 5457, "h": 3072, "name": "3410263ed65c42e4be84ef1d5bd879df", "format": 1, "size": 555481}, {"id": 85259734, "w": 5457, "h": 3072, "name": "7b4767d06f6b4ac79eb14441c4c9eedf", "format": 1, "size": 529919}, {"id": 85259732, "w": 5319, "h": 3072, "name": "83eca7a7a2534216bd562bb28feeab37", "format": 1, "size": 468097}, {"id": 84606621, "w": 4470, "h": 3072, "name": "8f31b45b309d4a1aabb5db01cd11bd14", "format": 1, "size": 458010}, {"id": 84606626, "w": 3504, "h": 3072, "name": "cfe4134290244c249617dc954c4dbbb0", "format": 1, "size": 441960}, {"id": 85259733, "w": 5457, "h": 3072, "name": "ef3f560245d241f4aea185c1677aa2de", "format": 1, "size": 470600}, {"id": 84606622, "w": 5101, "h": 3072, "name": "f8eb5c8a42de4c29aa7e0bf4265b3af3", "format": 1, "size": 572692}]}