{"id": "6940202785757469709", "type": 1, "user": 3048510, "time": 1615891882, "content": "#蔷薇少女十五周年大正团片#<br><br>“对人偶而言，没有所谓的死亡，只是去了很远的地方而已，所谓的存在，全都是观念而已，这孩子存在于这孩子里的观念，就在这里，那种确实的意识，当这孩子，觉得自己并不是该存在这时，那就和不存在是一样的，只会成为普通的物体而已，那是非常的寂寞，黑暗，冰冷，可悲的事。”<br><br>出境:<br>真红:幻颜（原po）<br>水银灯:曳尧<br>雪华绮晶:喵泽<br>雏莓:兔兔兔<br>金丝雀:程潜<br>苍星石:榆鹿<br>翠星石:狸昔<br>（排名不分先后随机打的）<br><br>摄影:奶师傅<br><br>棚子:奈雨工作室<br><br>妆娘:幻颜、鱼丁、支支<br><br>后期:大佐<br><br>感谢各位在百忙之中积极参与拍摄，也感谢各位为此团片进行的努力，大家辛苦了！！", "tags": [312, 1195], "images": [{"id": -7255361, "w": 9504, "h": 6336, "name": "0182675eb3074510bc69bf0b483bba3b", "format": 1, "size": 3757081}, {"id": -7255363, "w": 9504, "h": 6336, "name": "0906ddf412b7405d8aeef4188bcaf01e", "format": 1, "size": 3737054}, {"id": -7255354, "w": 6336, "h": 9504, "name": "0af0afebc5f7435093701f0761898434", "format": 1, "size": 3589505}, {"id": -7255362, "w": 9504, "h": 6336, "name": "74d749a0cbeb4d5ca33284f73822c8db", "format": 1, "size": 3559931}, {"id": -7255356, "w": 9504, "h": 6336, "name": "86cbcef79b45416baa15489172ae1eae", "format": 1, "size": 4814272}, {"id": -7255357, "w": 9504, "h": 6336, "name": "914aeb354c4a47389475b977810c799c", "format": 1, "size": 4225692}, {"id": -7255352, "w": 6336, "h": 9504, "name": "9b2e9e5f951c42829971051e645e275b", "format": 1, "size": 4914464}, {"id": -7255353, "w": 6336, "h": 9504, "name": "b839179c94eb4a129eb6283e2172b75c", "format": 1, "size": 4744113}, {"id": -7255358, "w": 6336, "h": 9504, "name": "d84df34d03cd44a2832d3071afa2fa7c", "format": 1, "size": 3589310}, {"id": -7255359, "w": 6336, "h": 9504, "name": "d894c868e15e4017acdfc1f6ddb98773", "format": 1, "size": 4242649}, {"id": -7255355, "w": 6336, "h": 9504, "name": "dbf736efb1bb4c5997eb47c8baaa5a4a", "format": 1, "size": 4431923}, {"id": -7255360, "w": 9504, "h": 6336, "name": "f86769cf670045749d798788d9af4727", "format": 1, "size": 5809855}, {"id": -7255351, "w": 714, "h": 9346, "name": "f9c6b5a026d1483e962bf85e531a9588", "format": 1, "size": 775976}]}