{"id": "6996594323156376607", "type": 1, "user": 110930792120, "time": 1629021560, "content": "#温漫7.31#cos场照#明日方舟絮雨<br><br>“如果可以的话，就将我当做在屋檐下避雨的旅人吧，请不要太在意我的事......”<br><br>眼罩没有调整好，都勒出痕迹了，救命！眼泪掉下来<br>絮雨真的是太好看了，太爱了！还有好多套絮雨可以慢慢发啦", "tags": [180056, 20849063, 977, 21153264, 399, 734271], "images": [{"id": -7333971, "w": 3376, "h": 6000, "name": "05a2da1a309a4ff48eaee3bdcab1e9f9", "format": 1, "size": 1936729}, {"id": -7333963, "w": 3376, "h": 6000, "name": "0eccfa07e2dc41648431ad655a3c56ef", "format": 1, "size": 1206427}, {"id": -7333967, "w": 6000, "h": 3376, "name": "4b73349fc19549078b114a64c3e6300a", "format": 1, "size": 1432688}, {"id": -7333969, "w": 6000, "h": 3376, "name": "6b48562dd13d4720a0c62512084fa8b7", "format": 1, "size": 1665001}, {"id": -7333965, "w": 6000, "h": 3376, "name": "9caba8096e704fa6901cf0c9c65cebcd", "format": 1, "size": 1116231}, {"id": -7333964, "w": 3376, "h": 6000, "name": "bc7c3bbae19c48fe91a85a551e722c55", "format": 1, "size": 1266742}, {"id": -7333970, "w": 4926, "h": 2771, "name": "c577165d111340a1976bbc63b07a8de4", "format": 1, "size": 1271617}, {"id": -7333968, "w": 3376, "h": 6000, "name": "e43bb27c9c824ab381425f285efe3f98", "format": 1, "size": 1792979}, {"id": -7333966, "w": 6000, "h": 3376, "name": "f73af2dcabe6472298f2268f45ecaa62", "format": 1, "size": 1105737}]}