{"id": "7025283193875995679", "type": 1, "user": 3935907182022333, "time": 1635701208, "content": "各位宝<br>阿七在这想让各位宝帮我看看那种的妆容好看些<br>p1-p4是10月30号化的打算去欢乐谷但是没票了，呜呜呜<br><br><br>p5-p7是之前上上个月拍的<br>不知道那种好看，就拿出来对比了，宝帮我看看吧", "tags": [19049, 399, 66890], "images": [{"id": -7395030, "w": 1080, "h": 1440, "name": "be7ab9bb3bae4e0a879e8645310c7583", "format": 1}, {"id": -7395029, "w": 1080, "h": 1440, "name": "f26052da9a4343c6a3979560ffb7e90a", "format": 1}, {"id": -7395028, "w": 1080, "h": 1440, "name": "ca1bb185cc244c97ba4b138e3aff93e7", "format": 1}, {"id": -7395027, "w": 1920, "h": 1920, "name": "ad247cf08d374018aea4d89011599c2a", "format": 1}, {"id": -7395026, "w": 1920, "h": 1920, "name": "7cf0f08424854d9e8acf323e2592709f", "format": 1}, {"id": -7395025, "w": 1920, "h": 1920, "name": "aee25a32d0f74c198d33ce998d737f79", "format": 1}, {"id": -7395024, "w": 1920, "h": 1920, "name": "9ef70be75bd74e7e82aa90c22b9b07cb", "format": 1}]}