{"id": "7064592705354996767", "type": 1, "user": 3418858, "time": 1644853667, "content": "* 。.:*・° ✰.。.:*・° <br>愿誓言与你同在 <br>愿真心永垂不朽<br>吾在此为你加冕 <br>✰.。.:* :° ✰.。.:*・°<br>花嫁 @包子8牛肉 <br>基佬 原po（妆面自理）<br>phx @元帅好养 @Mumei_Yu<br>ps @元帅好养 @包子8牛肉 <br>排版@风寒来无影 <br>抓住情人节的小尾巴 祝大家元宵节快乐 <br>ヾ(≧∪≦*)ノ〃", "tags": [1128], "images": [{"id": -7486841, "w": 1125, "h": 750, "name": "3e86c4d769da49f18520fb4d0f8fe0ad", "format": 5, "size": 16763}, {"id": -7486843, "w": 750, "h": 1125, "name": "53d334cbcfd143c0bf00e9317e2c7f0b", "format": 5, "size": 17233}, {"id": -7486844, "w": 1080, "h": 5222, "name": "5b5c7c818ab84c7492406e7731cbec35", "format": 5, "size": 97760}, {"id": -7486845, "w": 2000, "h": 8000, "name": "73ca931e63904e2fa3d951d8d1b87069", "format": 5, "size": 1950147}, {"id": -7486846, "w": 674, "h": 674, "name": "76af6083daa04e58962240ad35be00af", "format": 5, "size": 11128}, {"id": -7486842, "w": 1125, "h": 750, "name": "f85a202c9f5d417ead26980a4e2eec22", "format": 5, "size": 23384}]}