{"id": "7075012748882484236", "type": 1, "user": 3158226298221837, "time": 1647279772, "content": "生日快乐海未！！！今年的庆生服也超美的！HB to umi酱！Sonoda Umi世界第一！！！“无限延伸的大海 颜色如此温暖”号在图里欢迎扩列～（只是萌新", "tags": [2097, 2220, 30010], "images": [{"id": 175520630, "w": 1556, "h": 2253, "name": "0785de4fb1874c41a6320eeedd8aa45a", "format": 1, "size": 315299}, {"id": 175520627, "w": 2560, "h": 1600, "name": "3307f34783c54640abfcccf0d2b3a199", "format": 1, "size": 435174}, {"id": 175520629, "w": 2560, "h": 1600, "name": "9d94ef0e024e47d5a52991a3b14e651b", "format": 1, "size": 467371}, {"id": 175520628, "w": 2560, "h": 1600, "name": "cd3b21ea61ad44e092160ea46a530ce5", "format": 1, "size": 556026}]}