{"id": "7143557214576319495", "type": 1, "user": 1429015969672551, "time": 1663239024, "content": "————— 「 何 为 七 秀 」————————<br><br>「 师父，究竟何为七秀？ 」<br>「 鸢儿，你要记住，身托剑器板荡中，寄思乐舞太平时。不失我七秀风骨 」<br><br>叶芷青｜三三Senseii<br>荀鸢｜稀饭<br>摄影｜洛洛<br><br>存档", "tags": [1369, 399, 15, 278], "images": [{"id": -7630645, "w": 9504, "h": 5344, "name": "126c1d9595524b53aaf44ff45679fa2b", "format": 1, "size": 4590201}, {"id": -7630650, "w": 9504, "h": 5344, "name": "1c00d7db81a64ba9acd9ae948a6e6469", "format": 1, "size": 3689760}, {"id": -7630647, "w": 1600, "h": 7501, "name": "374d69a73e9a42a682febaed08a10fdd", "format": 1, "size": 1800151}, {"id": -7630646, "w": 1600, "h": 7536, "name": "3f9ba7bd512d47e2a9af1ecb2c6c70c5", "format": 1, "size": 1764685}, {"id": -7630648, "w": 1600, "h": 6353, "name": "b4efa323fb744029a864101e24a6eff9", "format": 1, "size": 1172453}, {"id": -7630649, "w": 6336, "h": 9504, "name": "dd724c6356334fb9970c940ce995bfe8", "format": 1, "size": 4821601}]}