{"id": "7147533623523023911", "type": 1, "user": 4239363629394763, "time": 1664164854, "content": "＃西木野真姬摇滚觉醒cos＃\u003Cbr\u003E喜欢欢迎点赞评论——\u003Cbr\u003E\u003Cbr\u003E「頂点極めさせて 私の美学， 頂点上りつめて 手が届かない高値のflower， I say“No.1”. My love only one!」\u003Cbr\u003E\u003Cbr\u003E摄影：阿卡林 合作愉快!下次继续!\u003Cbr\u003E妆造：樱靥 耶耶妆太强了我拍了一下午吃了个饭回家了它还在，俺好喜欢这个妆\u003Cbr\u003E后期：贝尔茉 贝老师整容的神!\u003Cbr\u003E后勤：零下九度 俺滴亲亲宝贝\u003Cbr\u003E碎碎念：是谁2022还在出ll 是我 那没事了", "tags": [399, 2097, 2056, 20092344, 21524289], "images": [{"id": 205577444, "w": 1680, "h": 1120, "name": "0c7c67d79e984791a06bc48ef2df0067", "format": 1}, {"id": 205577445, "w": 1680, "h": 1120, "name": "9e7e407b61bb4d0387d171f9d19f6192", "format": 1}, {"id": 205577446, "w": 1120, "h": 1680, "name": "78c5bd14e1bf4c8481009449d074dc12", "format": 1}, {"id": 205577447, "w": 1120, "h": 1680, "name": "de04f755a1a44164a2d3da6701630257", "format": 1}, {"id": 205577448, "w": 1680, "h": 1120, "name": "6ed0c52c794f495ea0cbbbfd5d2e4937", "format": 1}, {"id": 205577449, "w": 1120, "h": 1680, "name": "dcc00c0e2eb44292bf90bd4259a5f357", "format": 1}, {"id": 205577450, "w": 1120, "h": 1680, "name": "9a354173034a4ac684a3cbf639982419", "format": 1}, {"id": 205577451, "w": 1680, "h": 1120, "name": "0db0d194ea4d4d0992b7f12e96fbd7c3", "format": 1}, {"id": 205577452, "w": 1680, "h": 1120, "name": "c6e04ceaccf3495ebcdc6be8a93d288c", "format": 1}, {"id": 205577453, "w": 1680, "h": 1120, "name": "64981bc88ce14538bee91b8bab56b467", "format": 1}]}