{"id": "7154578796333505539", "type": 1, "user": 469907, "time": 1665805186, "content": "【COSPLAY正片】阴阳师—玉藻前•沁月凝霜—<br>この地に狐火をめぐらせて、運命の流れを変えよう<br>わたしは運命というものには決して屈しない<br><br>葛の葉、君の言うとおり<br>京都という桜の都は、実に根のもつれた所だ<br>————————————<br>玉藻前CN：翊重溟（原PO）<br>摄影：二泡<br>后期/排版/妆造：翊重溟<br>————————————<br>大舅是漂亮又骚气的男狐（？）又是P尾巴P到怀疑人生的一天，上次怀疑人生还是P大蛇的蛇崽崽们QAQQQQQQQ疫情严重坚持产片，我们都好棒！", "tags": [96846, 9866, 21040, 22132035, 64692, 20178, 399, 278, 1195, 21525019], "images": [{"id": -7648362, "w": 5472, "h": 3390, "name": "b558c2a2558c4a68bfcc371022f60d1c", "format": 1}, {"id": -7648361, "w": 5472, "h": 3648, "name": "8965c0df684a491fb801b43d4033ba13", "format": 1}, {"id": -7648360, "w": 5207, "h": 3422, "name": "7871362f3fac4b8f8dce72d0016a9312", "format": 1}, {"id": -7648359, "w": 3648, "h": 6340, "name": "f09f65f8b75a45e29780ab337ac3163e", "format": 1}, {"id": -7648358, "w": 3648, "h": 6396, "name": "7ac371b039a34eaab8f3118384f6fa60", "format": 1}, {"id": -7648357, "w": 3648, "h": 5472, "name": "3b142d616fda4f499115c0f11fc804b1", "format": 1}, {"id": -7648356, "w": 3648, "h": 6853, "name": "0b331bb721cb4746b5851ad587591f3c", "format": 1}, {"id": -7648355, "w": 8670, "h": 4858, "name": "29db22152db64a378fd5259ac35c7afb", "format": 1}, {"id": -7648354, "w": 3648, "h": 5855, "name": "14b68710dfea4d3391fc326c47aec6d7", "format": 1}, {"id": -7648353, "w": 1509, "h": 14999, "name": "b225b4086a514dd89f7fdde5ba72421b", "format": 1}, {"id": -7648352, "w": 6193, "h": 3805, "name": "33ffb87d2ae64db3b5085a82440d9729", "format": 1}]}