{"id": "7172402957042850823", "type": 1, "user": 70792319341357, "time": 1669955197, "content": "阴阳师百闻牌·藤姬<br><br>——————————————————<br><br>“眼前繁花盛景，不妨幻梦不醒。”<br>    “但浮世缥缈一梦，亦如花开一瞬。”<br><br>出镜：po<br>摄影：洛洛<br>后期：黑然<br><br>——————————————————<br><br>一些碎碎念，当你很喜欢一个角色的时候，创作的过程会有比较复杂的情绪。出到喜欢的角色很开心，成片出来又觉得没有表现出角色的性格又有点失落。本来计划去拍个夜景，但是赶上一些和角色服装有关不可言说的原因没有成行。希望明年有机会二刷！老规矩，感谢所有参与创造的亲友。", "tags": [96846, 399, 1195, 20170429, 20904692, 22220632, 21525019, 20407128], "images": [{"id": -7677153, "w": 2730, "h": 4096, "name": "f0fe07c19a0442f884801568995c7a09", "format": 1}, {"id": -7677152, "w": 2730, "h": 4096, "name": "7e935bfbabf14606847f31c0d532884a", "format": 1}, {"id": -7677151, "w": 2730, "h": 4096, "name": "9b5084ca6576453896f2c30aa24b18c1", "format": 1}, {"id": -7677150, "w": 4096, "h": 2302, "name": "5672bb0f2c844a14adde466f2642006e", "format": 1}, {"id": -7677149, "w": 2730, "h": 4096, "name": "702bbd73f1754baab9dbdf251c4e4585", "format": 1}, {"id": -7677148, "w": 4096, "h": 2302, "name": "72784fe9b02e4583b45bd139bfb66dac", "format": 1}, {"id": -7677147, "w": 2730, "h": 4096, "name": "57d75b91ab2c4dbf82d7d6850b7186f3", "format": 1}, {"id": -7677146, "w": 2730, "h": 4096, "name": "34149e4334d1407687eb5ba8ff7e9fc0", "format": 1}, {"id": -7677145, "w": 2730, "h": 4096, "name": "0d297878e7c743c6af5e88a444d85b40", "format": 1}]}