{"id": "7193987701870173242", "type": 1, "user": 111036851776, "time": 1674980787, "content": "#从零开始的异世界生活#蕾姆#1.18号郴州萌元漫展#场照#<br>出镜：萧樱樱原po<br>摄影：暮禾<br>后期：暮禾<br>妆容：萧樱樱<br>本当の愛に色があるとしたら、それは青に違いない.<br>如果真爱有颜色，那一定是蓝色.<br>あなたと出会ったのは何かの縁ですね.<br>遇到你真是一种缘分呢.", "tags": [71693, 399, 71978, 1314], "images": [{"id": -7710967, "w": 3762, "h": 2508, "name": "da280a3ed9384740aa4e84e1bd85531d", "format": 1}, {"id": -7710966, "w": 3762, "h": 2508, "name": "560aaf2615c7441896fec1b6de26d946", "format": 1}, {"id": -7710965, "w": 3008, "h": 2005, "name": "51057db3e7d14ad1a23902d9e74f123d", "format": 1}, {"id": -7710964, "w": 3762, "h": 2508, "name": "8e561fbef9e849849e15c75a24b00e87", "format": 1}, {"id": -7710963, "w": 3762, "h": 2508, "name": "d33599e39d6b48ac94b06599bb0f5479", "format": 1}, {"id": -7710962, "w": 2508, "h": 3762, "name": "4649d7d06b0140d48e6203de22048dfd", "format": 1}]}