{"id": "7197419273667484709", "type": 1, "user": 778871739268414, "time": 1675779762, "content": "原初天使设定（在线征名\u003Cbr\u003E右眼一直带着玫瑰花因为诅咒（和安哥不是同一种）\u003Cbr\u003E诅咒发作会右眼疼加头疼严重全身抽搐\u003Cbr\u003E（趣）\u003Cbr\u003E头疼是一阵一阵的剧痛所以发作时她多半会晕过去\u003Cbr\u003E头上那个是角（后面那个是发带啊淦不是连在一起的）\u003Cbr\u003E代号『天使R』\u003Cbr\u003E喜欢和艾蒂待在一起\u003Cbr\u003E\u003Cbr\u003E元力技能火焰玫瑰和金棘刃（讲白了两把匕首）\u003Cbr\u003E名字姓林和玫\u003Cbr\u003E俩字\u003Cbr\u003E相中给无偿\u003Cbr\u003E别问我为什么公主内八问就是我懒得改\u003Cbr\u003E有建议就提\u003Cbr\u003E有意见也提（反正姐不改😋）", "tags": [5798, 522, 21134220, 20155942, 22212263, 22175758, 22028361, 22270682, 316639], "images": [{"id": 222446619, "w": 1080, "h": 1440, "name": "4ecf502d3d584e17852b8dc66e81673d", "format": 2}]}