{"id": "7219130845448117309", "type": 1, "user": 928422209002365, "time": 1680834881, "content": "Yoga|瑜伽体式详解|新月式\u003Cbr\u003E昨天分享了骑马式不知道大家学会了么？今天分享的这个体式和骑马式很接近——新月式！这个体式可以很好的伸展全身的肌肉线条；在理疗方面，可以缓解久坐引起的腰背不适；伸展到腹前侧，促进腹股沟淋巴系统排毒；纠正骨盆的位置！总之也是一个功效多多的体式，姐妹们快练起来了！\u003Cbr\u003E——\u003Cbr\u003E🔴体式口令；\u003Cbr\u003E首先四脚板凳式进入，随着吸气右腿迈至双手之间；左腿向勾伸直；双手扶髋；随着吸气手臂向上，头顶合十；呼气沉髋向下，挑胸腔后弯；保持3-5个呼吸；吸气身体慢慢回正，呼气放松还原；换另一侧；\u003Cbr\u003E——\u003Cbr\u003E🔴动作要领；\u003Cbr\u003E1⃣保持骨盆的中正；\u003Cbr\u003E2⃣收腹收肋骨，核心稳定；保持腰椎两侧对等伸展；\u003Cbr\u003E3⃣挑胸腔向上，肩膀下沉，远离耳朵，头顶心向上延伸；\u003Cbr\u003E4⃣保持双腿肌肉收紧上提，后腿脚背压实垫子；前脚脚趾向下扎根，注意膝盖不要超脚尖，大腿肌肉收紧上提；同时双腿肌肉外侧向中线靠拢；\u003Cbr\u003E5⃣耻骨找肚脐；肚脐上提找胸腔；胸腔上提找下巴；下巴上提找头顶；整个身体成月牙形状；", "tags": [3335, 55336, 34215, 22338417], "images": [{"id": 229884669, "w": 1280, "h": 1706, "name": "51d6e013b6ce444ba48b8487e1e0cddb", "format": 7, "size": 116488}, {"id": 229884670, "w": 1280, "h": 1706, "name": "961454d909094ca7aaef9b7545c6272b", "format": 7, "size": 122082}]}